mkdocs_mcq/__init__.py
mkdocs_mcq/assets/mcq.css
mkdocs_mcq/assets/mcq.js
mkdocs_mcq/plugin.py
mkdocs_mcq-0.1.4.dist-info/WHEEL
mkdocs_mcq-0.1.4.dist-info/entry_points.txt
mkdocs_mcq-0.1.4.dist-info/METADATA
mkdocs_mcq-0.1.4.dist-info/RECORD
