Metadata-Version: 2.3
Name: mkdocs-mcq
Version: 0.1.4
Summary: MkDocs plugin for multiple choice quizzes
Author: broktoram
Author-email: broktoram <broktoram@gmail.com>
License: MIT
Requires-Dist: mkdocs>=1.5
Requires-Dist: pymdown-extensions>=10.0
Requires-Dist: pyyaml>=6.0
Requires-Dist: mkdocs-material>=9.0 ; extra == 'docs'
Requires-Python: >=3.9
Provides-Extra: docs
